inventaire_obs/__init__.py
inventaire_obs/inventaire_obs.py
inventaire_obs-0.1.1.dist-info/WHEEL
inventaire_obs-0.1.1.dist-info/METADATA
inventaire_obs-0.1.1.dist-info/RECORD
