Metadata-Version: 2.1
Name: inventaire-obs
Version: 0.1.1
Summary: Script d'inventaire OBS
Author: Thomas Christory
Author-email: thomas@christory.net
Requires-Python: >=3.8,<4.0
Classifier: Programming Language :: Python :: 3
Classifier: Programming Language :: Python :: 3.8
Requires-Dist: click (>=7.1.2,<8.0.0)
Requires-Dist: netmiko (>=3.1.1,<4.0.0)
